aiocomelit/__init__.py
aiocomelit/api.py
aiocomelit/const.py
aiocomelit/exceptions.py
aiocomelit/py.typed
aiocomelit-1.1.2.dist-info/METADATA
aiocomelit-1.1.2.dist-info/WHEEL
aiocomelit-1.1.2.dist-info/licenses/LICENSE
aiocomelit-1.1.2.dist-info/RECORD
