Metadata-Version: 2.4
Name: aiocomelit
Version: 1.1.2
Summary: Python library to control Comelit Simplehome
License-Expression: Apache-2.0
License-File: LICENSE
Author: Simone Chemelli
Author-email: simone.chemelli@gmail.com
Requires-Python: >=3.12
Classifier: Development Status :: 5 - Production/Stable
Classifier: Intended Audience :: Developers
Classifier: Natural Language :: English
Classifier: Operating System :: OS Independent
Classifier: Topic :: Software Development :: Libraries
Requires-Dist: aiohttp (>=3.12.7)
Requires-Dist: colorlog
Requires-Dist: pint
Project-URL: Bug Tracker, https://github.com/chemelli74/aiocomelit/issues
Project-URL: Changelog, https://github.com/chemelli74/aiocomelit/blob/main/CHANGELOG.md
Project-URL: Homepage, https://github.com/chemelli74/aiocomelit
